etiq.cp312-win_amd64.pyd
etiq.pyi
etiq/db/migrations/20230615-hello-migration.sql
etiq/db/migrations/20230817-project-deletion-column.sql
etiq/db/migrations/20230912-licensing.webapi.sql
etiq/db/migrations/20240208-issue-aggregate-params.sql
etiq/db/migrations/20240307-data-profile-condition.sql
etiq/db/migrations/20240321-data-table-str-id.sql
etiq/db/migrations/version10.sql
etiq/db/migrations/version11.sql
etiq/db/migrations/version12.sql
etiq/db/migrations/version13.sql
etiq/db/migrations/version14.sql
etiq/db/migrations/version15.sql
etiq/db/migrations/version15.webapi.sql
etiq/db/migrations/version2.sql
etiq/db/migrations/version3.sql
etiq/db/migrations/version4.sql
etiq/db/migrations/version5.sql
etiq/db/migrations/version6.sql
etiq/db/migrations/version7.sql
etiq/db/migrations/version8.sql
etiq/db/migrations/version8.webapi.sql
etiq/db/migrations/version9.sql
etiq/sample_data/adult_data_sampled.csv
etiq/sample_data/adult_data_sampled.pkl
etiq/sample_data/adult_protected_train_resampled.pkl
etiq/sample_data/adult_x_train_resampled.pkl
etiq/sample_data/adult_y_train_resampled.pkl
etiq/sample_data/adultdata.pkl
etiq/sample_data/adultdataset.csv
etiq/sample_data/encoded_adult.csv
etiq/sample_data/encoded_adult.pkl
etiq-1.6.0.dist-info/LICENSE
etiq-1.6.0.dist-info/METADATA
etiq-1.6.0.dist-info/WHEEL
etiq-1.6.0.dist-info/top_level.txt
etiq-1.6.0.dist-info/RECORD
