Metadata-Version: 2.1
Name: etiq
Version: 1.6.0
Summary: ETIQ.ai ML Testing library
Home-page: https://etiq.ai/
Author: ETIQ AI
Author-email: devops@etiq.ai
Keywords: ai,bias,etiq,fairness
Classifier: Development Status :: 5 - Production/Stable
Classifier: Environment :: Console
Classifier: Environment :: MacOS X
Classifier: Environment :: Win32 (MS Windows)
Classifier: Framework :: IPython
Classifier: Framework :: Jupyter
Classifier: Intended Audience :: Science/Research
Classifier: License :: Other/Proprietary License
Classifier: Natural Language :: English
Classifier: Programming Language :: Python :: 3.8
Classifier: Programming Language :: Python :: 3.9
Classifier: Programming Language :: Python :: 3.10
Classifier: Programming Language :: Python :: 3.11
Classifier: Programming Language :: Python :: 3.12
Classifier: Topic :: Scientific/Engineering
Classifier: Topic :: Scientific/Engineering :: Artificial Intelligence
Classifier: Topic :: Scientific/Engineering :: Information Analysis
Requires-Python: >=3.8,<3.13
License-File: LICENSE
Requires-Dist: platformdirs
Requires-Dist: numpy<=1.26.4,>=1.21
Requires-Dist: pandas<2,>=1.3.5
Requires-Dist: sqlalchemy<2,>=1.4
Requires-Dist: scikit-learn
Requires-Dist: xgboost>1.5.1
Requires-Dist: requests
Requires-Dist: shortuuid
Provides-Extra: all
Requires-Dist: great-expectations; extra == "all"
